pyliblorawan/__init__.py
pyliblorawan/models.py
pyliblorawan/py.typed
pyliblorawan/devices/browan/tbhh100.py
pyliblorawan/devices/browan/tbms100.py
pyliblorawan/devices/elsys/erseco.py
pyliblorawan/devices/mclimate/co2.py
pyliblorawan/devices/merryiot/airqualityco2.py
pyliblorawan/devices/milesight/common.py
pyliblorawan/devices/milesight/em300th.py
pyliblorawan/devices/sensecap/t1000.py
pyliblorawan/devices/tektelic/vivid.py
pyliblorawan/helpers/exceptions.py
pyliblorawan/helpers/loracloud.py
pyliblorawan/network_servers/helium.py
pyliblorawan/network_servers/helpers.py
pyliblorawan/network_servers/orange.py
pyliblorawan/network_servers/ttn.py
pyliblorawan-0.5.1.dist-info/LICENSE.md
pyliblorawan-0.5.1.dist-info/METADATA
pyliblorawan-0.5.1.dist-info/WHEEL
pyliblorawan-0.5.1.dist-info/top_level.txt
pyliblorawan-0.5.1.dist-info/RECORD
