Metadata-Version: 2.2
Name: pyliblorawan
Version: 0.5.1
Summary: LoRaWAN network servers and devices codec library
Author: Oliv'
License:                                  Apache License
Project-URL: Homepage, https://gitlab.com/oliv4945/pyliblorawan
Project-URL: Bug Tracker, https://gitlab.com/oliv4945/pyliblorawan/-/issues
Keywords: LoRaWAN,codec,network server,lora
Classifier: License :: OSI Approved :: Apache Software License
Classifier: Operating System :: OS Independent
Classifier: Programming Language :: Python
Classifier: Programming Language :: Python :: 3
Classifier: Topic :: Home Automation
Classifier: Topic :: Software Development :: Libraries
Classifier: Topic :: Software Development :: Libraries :: Python Modules
Requires-Python: >=3.9
License-File: LICENSE.md
Requires-Dist: aiohttp>=3.8.5
Provides-Extra: dev
Requires-Dist: aioresponses>=0.7.0; extra == "dev"
Requires-Dist: pytest>=7.3.0; extra == "dev"
Requires-Dist: pytest-asyncio>=0.21.0; extra == "dev"
Requires-Dist: pytest-cov>=4.1.0; extra == "dev"
